sf_toolkit/__init__.py
sf_toolkit/_models.py
sf_toolkit/apimodels.py
sf_toolkit/async_utils.py
sf_toolkit/auth/__init__.py
sf_toolkit/auth/_httpx.py
sf_toolkit/auth/login_cli.py
sf_toolkit/auth/login_lazy.py
sf_toolkit/auth/login_oauth.py
sf_toolkit/auth/login_soap.py
sf_toolkit/auth/types.py
sf_toolkit/client.py
sf_toolkit/data/__init__.py
sf_toolkit/data/bulk.py
sf_toolkit/data/fields.py
sf_toolkit/data/query_builder.py
sf_toolkit/data/sobject.py
sf_toolkit/data/standard_schemas.py
sf_toolkit/data/transformers.py
sf_toolkit/exceptions.py
sf_toolkit/formatting.py
sf_toolkit/io/__init__.py
sf_toolkit/io/api.py
sf_toolkit/io/file.py
sf_toolkit/logger.py
sf_toolkit/metrics.py
sf_toolkit/py.typed
sf_toolkit/resources/__init__.py
sf_toolkit/resources/base.py
sf_toolkit/resources/metadata.py
sf_toolkit/resources/tooling.py
sf_toolkit-0.5.8.dist-info/METADATA
sf_toolkit-0.5.8.dist-info/WHEEL
sf_toolkit-0.5.8.dist-info/licenses/LICENSE.txt
sf_toolkit-0.5.8.dist-info/RECORD
